{
  "descriptionHash": "AE4CE0ECB58684C248B47FBEF5D1F1EA5B96F1172EAFBB432BBF05BAE9B86F4414365EAC06888CE78E17426CB4B0F9347E0BFE4804AEBBC835A49BBFDE4921B2",
  "descriptionLocation": "../../../../tsp-output/@typespec/openapi3/openapi.BunnyApi.yaml",
  "lockFileVersion": "1.0.0",
  "kiotaVersion": "1.18.0",
  "clientClassName": "BunnyApiClient",
  "clientNamespaceName": "BunnyApiClient",
  "language": "CLI",
  "usesBackingStore": false,
  "excludeBackwardCompatible": true,
  "includeAdditionalData": true,
  "disableSSLValidation": false,
  "serializers": [
    "Microsoft.Kiota.Serialization.Json.JsonSerializationWriterFactory",
    "Microsoft.Kiota.Serialization.Text.TextSerializationWriterFactory",
    "Microsoft.Kiota.Serialization.Form.FormSerializationWriterFactory",
    "Microsoft.Kiota.Serialization.Multipart.MultipartSerializationWriterFactory"
  ],
  "deserializers": [
    "Microsoft.Kiota.Serialization.Json.JsonParseNodeFactory",
    "Microsoft.Kiota.Serialization.Text.TextParseNodeFactory",
    "Microsoft.Kiota.Serialization.Form.FormParseNodeFactory"
  ],
  "structuredMimeTypes": [
    "application/json",
    "text/plain;q=0.9",
    "application/x-www-form-urlencoded;q=0.2",
    "multipart/form-data;q=0.1"
  ],
  "includePatterns": [],
  "excludePatterns": [],
  "disabledValidationRules": []
}